click_repl/__init__.py
click_repl/exceptions.py
click_repl-0.2.0.dist-info/LICENSE
click_repl-0.2.0.dist-info/METADATA
click_repl-0.2.0.dist-info/WHEEL
click_repl-0.2.0.dist-info/top_level.txt
click_repl-0.2.0.dist-info/RECORD
